<?xml version="1.0" encoding="UTF-8" ?>
<r xmlns="http://pear.php.net/dtd/rest.release2" xmlns:xsi="http://www.w3.org/2001/XMLSchema-instance" xmlns:xlink="http://www.w3.org/1999/xlink" xsi:schemaLocation="http://pear.php.net/dtd/rest.release2 http://pear.php.net/dtd/rest.release2.xsd">
    <p xlink:href="/pear/rest/p/simpleid">SimpleID</p>
    <c>simpleid.org</c>
    <v>0.9</v>
    <a>0.9</a>
    <mp>5.2.0</mp>
    <st>beta</st>
    <l>GPL</l>
    <m>kmo</m>
    <s>SimpleID is a simple, personal OpenID provider</s>
    <d>SimpleID is a simple, personal OpenID provider written in PHP.</d>
    <da>2014-04-17 23:24:58</da>
    <n>
See README.txt
 </n>
    <f>172685</f>
    <g>http://downloads.sourceforge.net/simpleid/SimpleID-0.9</g>
    <x xlink:href="package.0.9.xml"/>
</r>